{
  "project_info": {
    "project_number": "4773735112",
    "firebase_url": "https://trackonpark-9a32f.firebaseio.com",
    "project_id": "trackonpark-9a32f",
    "storage_bucket": "trackonpark-9a32f.appspot.com"
  },
  "client": [
    {
      "client_info": {
        "mobilesdk_app_id": "1:4773735112:android:63215db36a77a9252a13fd",
        "android_client_info": {
          "package_name": "com.spit.CarTrack"
        }
      },
      "oauth_client": [
        {
          "client_id": "4773735112-mh0m43i56h39pekmf94cojujsrmurd2s.apps.googleusercontent.com",
          "client_type": 1,
          "android_info": {
            "package_name": "com.spit.CarTrack",
            "certificate_hash": "60510fa2b4f0fa7e3be99b7a0d6468f287c07008"
          }
        },
        {
          "client_id": "4773735112-t48t56otl1b9ap6urfd593ngm330vq4h.apps.googleusercontent.com",
          "client_type": 3
        }
      ],
      "api_key": [
        {
          "current_key": "AIzaSyBrMv1wzExgQi4Pcse344Wo-RYGZPBoWNs"
        }
      ],
      "services": {
        "appinvite_service": {
          "other_platform_oauth_client": [
            {
              "client_id": "4773735112-t48t56otl1b9ap6urfd593ngm330vq4h.apps.googleusercontent.com",
              "client_type": 3
            }
          ]
        }
      }
    }
  ],
  "configuration_version": "1"
}